Workbook

Sheet Executive Summary
A1: TRADING PLATFORM | DELIVERY PLAN
A2: Evidence baseline | B2: 2026-10-14; repository + docs/test_results.md dated 2026-10-11
A3: Purpose | B3: Databricks trading data processing and daily P&L proof of concept
A4: Current implementation | B4: Six-task Databricks Workflow; 10 Delta tables in cibc.bronze/silver/gold; synthetic trades; Yahoo Finance prices; position/P&L; audit/rejects; notebooks/SQL.
A5: Not implemented / not evidenced | B5: Deployed dashboard; approved market-data contract; non-dev Bundle targets/CI; automated alerting; production identity; approved retention/RTO/RPO; successful second same-input Databricks run.
A6: Schedule | B6: Proposed 8-week / four 2-week sprints. 40 story points at assumed 10 points per sprint; no capacity reserve. Relative weeks only, not approved calendar dates.
A7: Prototype limitation | B7: USD cash equities; ten in-code instruments; approximate NYSE calendar; full-history recompute; simplified daily P&L; fees, FX, corporate actions, dividends, settlement cash, and short-sale mechanics excluded.
A8: Jira import | B8: Temporary planning IDs; map planning key to custom field, issue hierarchy and Epic Link to Jira fields, and replace planning Epic Link values with created Jira epic keys where required.
A9: Status legend | B9: IMPLEMENTED = code/config/test/run evidence; PARTIALLY IMPLEMENTED = supporting behavior with a material gap; PLANNED = not delivered; TO BE CONFIRMED = evidence/owner absent.
A10: Metric | B10: Value | C10: Interpretation
A11: Business requirements | B11: =COUNTA('Business Req'!A:A)-1 | C11: Eight business outcomes
A12: Functional requirements | B12: =COUNTA('Functional Req'!A:A)-1 | C12: Detailed system behaviors
A13: Jira epics | B13: =COUNTA(Epics!A:A)-1 | C13: Planning hierarchy
A14: Jira stories | B14: =COUNTA(Stories!A:A)-1 | C14: Includes current-state and proposed work
A15: Planned sprint points | B15: =SUM(Sprints!E2:E5) | C15: Proposed 8-week baseline; no reserve
A16: Physical dictionary columns | B16: =COUNTA('Data Dictionary'!G:G)-1 | C16: DDL-derived across 10 tables

Sheet Business Req
A1: BR ID | B1: Requirement | C1: Business justification | D1: Priority | E1: Acceptance criteria | F1: Dependencies | G1: Implementation status | H1: Functional requirements
A2: BR-001 | B2: Ingest trade transactions from an agreed source. | C2: Provide complete, traceable trade activity for positions and P&L. | D2: Must | E2: A valid input snapshot is recorded in Bronze with source and run lineage; invalid file structure fails before replacing the prior snapshot. | F2: Trade source contract; Unity Catalog Volume | G2: IMPLEMENTED | H2: FR-001; FR-003; FR-004; FR-005; FR-013
A3: BR-002 | B3: Ingest daily market prices for supported instruments. | C3: Provide valuation marks and P&L inputs. | D3: Must | E3: Requested daily prices are recorded with source/date/currency lineage; missing expected sessions are visible and block incomplete Silver publication. | F3: Provider availability and ticker universe | G3: IMPLEMENTED | H3: FR-002; FR-003; FR-005; FR-013
A4: BR-003 | B4: Maintain accurate trade records, including corrections and duplicates. | C4: Prevent stale or ambiguous executions from contaminating financial results. | D4: Must | E4: One latest valid version per trade_id is used; invalid/ambiguous latest versions are excluded and explained; source-history limitations are disclosed. | F4: Trade version contract; immutable source history decision | G4: PARTIALLY IMPLEMENTED | H4: FR-004; FR-005; FR-009; FR-013
A5: BR-004 | B5: Calculate historical and daily positions by date, book, counterparty, instrument, and currency. | C5: Give trading users a reproducible inventory view. | D5: Must | E5: Daily signed net quantities reconcile to accepted trades and carry forward on expected sessions; source corrections update affected dates. | F5: Validated trades; supported trading calendar | G5: IMPLEMENTED | H5: FR-006; FR-007; FR-009
A6: BR-005 | B6: Calculate daily position valuation and daily P&L. | C6: Provide transparent daily equity valuation and trading P&L. | D6: Must | E6: Gold contains daily valuation and decomposed daily P&L; missing marks/baselines remain NULL with breaks; quantity changes are not misattributed to price movement. | F6: Positions; validated price history; approved methodology | G6: IMPLEMENTED | H6: FR-007; FR-008; FR-009
A7: BR-006 | B7: Provide trading, P&L, and operational reporting. | C7: Make outcomes and exceptions accessible to users. | D7: Should | E7: Read-only report/query surfaces expose run status, rejects, positions, P&L, and breaks; a dashboard is delivered only after user acceptance criteria are agreed. | F7: Reporting requirements; Gold datasets | G7: PARTIALLY IMPLEMENTED | H7: FR-010; FR-011
A8: BR-007 | B8: Support operational monitoring, auditability, and error investigation. | C8: Make failed and incomplete processing diagnosable. | D8: Must | E8: Every task attempt records status, timestamps, row counts, issue counts, and error details; valuation breaks and rejects retain lineage. | F8: Audit and reject tables; operations ownership | G8: PARTIALLY IMPLEMENTED | H8: FR-005; FR-011; FR-012; FR-013
A9: BR-008 | B9: Automate repeatable daily processing with controlled reruns. | C9: Reduce manual handling and support predictable delivery. | D9: Must | E9: A parameterized workflow executes the dependency graph; retry/rerun behavior is tested; production schedule remains disabled until readiness sign-off. | F9: Production environment, source SLA, support model | G9: PARTIALLY IMPLEMENTED | H9: FR-012; FR-013

Sheet Functional Req
A1: FR ID | B1: Parent BR | C1: Functional description | D1: Input | E1: Processing logic | F1: Expected output | G1: Business rules | H1: Error handling | I1: Acceptance criteria | J1: Components | K1: Implementation status | L1: Jira stories
A2: FR-001 | B2: BR-001 | C2: Read the 14-column trade CSV from the configured Unity Catalog Volume as raw strings. | D2: CSV snapshot at configured Volume path | E2: Validate exact header, non-empty content, and structural integrity before write; remove identical in-batch rows. | F2: cibc.bronze.trades snapshot with source_file, ingestion_timestamp, run_id | G2: All source columns remain raw strings in Bronze; different trade versions remain distinct. | H2: Fail before overwrite for bad header, empty file, corrupt row, or unreadable source; audit failure. | I2: A valid fixture replaces Bronze with distinct raw rows and correct lineage; invalid fixtures leave the previous snapshot unchanged. | J2: scripts/generate_trades.py; bronze/ingest_trades.py; UC Volume | K2: IMPLEMENTED | L2: TMP-011
A3: FR-002 | B3: BR-002 | C3: Download daily unadjusted closing prices for requested tickers and inclusive date range. | D3: Ticker/date parameters; yfinance public endpoint | E3: Retry transient provider exceptions up to 3 attempts; normalize response shapes; record close, USD, source API, ingestion timestamp, run id. | F3: cibc.bronze.market_prices | G3: Default 10 configured symbols and seven-day lookback; no credentials currently used. | H3: Fail on empty expected response, missing ticker, malformed or ambiguous response; no synthetic price is invented. | I3: Fixture tests cover flat and MultiIndex payloads; missing expected sessions are surfaced. | J3: bronze/ingest_prices.py; yfinance | K3: IMPLEMENTED | L3: TMP-013; TMP-014
A4: FR-003 | B4: BR-001 | C4: Validate source schemas and convert raw values into typed Silver fields. | D4: Bronze trades and prices | E4: Use try_cast into DATE, TIMESTAMP, INT, DECIMAL(18,6), and preserve raw values in rejects. | F4: Typed Silver trades/prices and reject tables | G4: Financial amounts and quantities use DECIMAL; source IDs remain STRING. | H4: Uncastable/invalid records are quarantined; incomplete expected price sessions prevent Silver merge. | I4: Schema and cast tests verify typed values and preserve reason codes. | J4: silver/process_trades.py; silver/process_prices.py | K4: IMPLEMENTED | L4: TMP-015; TMP-016
A5: FR-004 | B5: BR-003 | C5: Select the highest trade version, then latest modified_timestamp, per trade_id. | D5: Bronze trade snapshot | E5: Reject exact duplicates; reject conflicting ties; do not fall back when the latest version is invalid or ambiguous. | F5: At most one accepted Silver row per trade_id | G5: Only trade IDs still in the new snapshot are removed when latest is unusable; absent IDs are not deleted from Silver. | H5: Ambiguity and unorderable version are quarantined with reason codes. | I5: Fixtures cover valid correction, exact duplicate, conflicting tie, invalid latest version, and lower version. | J5: silver/process_trades.py; silver/trades_rejects | K5: IMPLEMENTED | L5: TMP-015; TMP-012
A6: FR-005 | B6: BR-007 | C6: Apply trade and price data-quality rules and retain actionable rejects. | D6: Raw trade and price records | E6: Validate identifiers, mapping, side/quantity, positive prices, currency, dates/calendar, settlement, version, and price key uniqueness. | F6: Silver accepted datasets, rejects with reason(s), valuation breaks | G6: BUY is positive and SELL is negative; only USD and configured instruments are supported. | H6: Reject invalid rows; fail task where missing expected prices make the requested output incomplete. | I6: Each configured invalid fixture maps to expected reason(s); reject merge is idempotent. | J6: Silver processors; common/rejects.py; gold/break_report.py | K6: IMPLEMENTED | L6: TMP-015; TMP-016
A7: FR-006 | B7: BR-004 | C7: Calculate daily and cumulative signed positions at the defined Gold grain. | D7: Silver accepted trades | E7: Aggregate daily buy/sell/net then cumulative SUM(quantity) over trading sessions by book/counterparty/instrument/currency. | F7: cibc.gold.positions | G7: Position key is valuation_date + book_id + counterparty_id + instrument_id + currency; short quantities are allowed. | H7: Empty sources or duplicate price keys fail without publishing; source-scoped merge reconciles history. | I7: Daily/cumulative quantities match independent aggregation including no-trade days and short/flat positions. | J7: gold/build_positions.py; gold/positions | K7: IMPLEMENTED | L7: TMP-017
A8: FR-007 | B8: BR-005 | C8: Value positions using same-day close in the same currency. | D8: Gold positions; Silver prices | E8: market_value = closing_position_quantity * closing_price at exact valuation date and currency. | F8: Gold position closing_price and market_value; missing-price break | G8: Missing close remains NULL; quantities are unaffected; a flat/no-activity position does not require a mark. | H8: Missing non-flat position marks create OPEN valuation breaks. | I8: Valuation matches independent Decimal calculation; missing close produces NULL and a break. | J8: gold/build_positions.py; gold/valuation_breaks | K8: IMPLEMENTED | L8: TMP-017
A9: FR-008 | B9: BR-005 | C9: Calculate daily equity P&L separating opening-position price movement from trade-day economics. | D9: Gold positions; Silver trades; Silver price history | E9: OpeningQty*(CurrentClose-PreviousClose) + (DailyNetQty*CurrentClose - SignedTradeConsideration); new positions with zero opening quantity use trade-day term only. | F9: cibc.gold.daily_pnl with status and valuation inputs | G9: Latest prior close is the previous baseline; current close is exact date. Missing required current/baseline price leaves daily_pnl NULL. | H9: Create missing-current-price or missing-baseline break; never treat NULL as zero. | I9: Independent test examples match; activity quantity changes do not create false opening-position P&L. | J9: gold/calculate_daily_pnl.py; gold/daily_pnl | K9: IMPLEMENTED | L9: TMP-018
A10: FR-009 | B10: BR-003 | C10: Retain historical accepted prices, reject history, audit/break history, and recompute affected Gold history after corrections. | D10: Full Silver history and correction snapshot | E10: Prices/rejects MERGE by business key; Gold recomputes full Silver history; changed business values update scoped Gold rows. | F10: Historical Silver/Gold datasets and lineage | G10: Bronze trades is only the latest snapshot; disappeared IDs are not purged from Silver; Gold delete scope cannot remove absent instruments/symbols. | H10: Require reconciliation and manual remediation for missing historical scope; expose limitations. | I10: Backdated correction updates affected dates; retention and deletion semantics are documented before production. | J10: Bronze/Silver/Gold Delta tables; Delta history | K10: PARTIALLY IMPLEMENTED | L10: TMP-012; TMP-017; TMP-018
A11: FR-010 | B11: BR-006 | C11: Provide read-only operational and business reporting over run logs, rejects, positions, P&L, and breaks. | D11: Gold/Silver Delta tables and Jobs API | E11: Existing notebook report and demo SQL show status, metrics, rejects, positions, P&L, breaks; proposed dashboard consumes curated Gold. | F11: Notebook/SQL reporting now; dashboard dataset/view and dashboard proposed | G11: Do not claim Databricks SQL dashboard exists; current report is notebook-based. | H11: Report shows NOT AVAILABLE when audit/API data is absent rather than inventing metrics. | I11: Users reconcile report totals to tables; dashboard acceptance criteria and audience approved before build. | J11: notebooks/02_pipeline_report.py; docs/demo_queries.sql; proposed dashboard | K11: PARTIALLY IMPLEMENTED | L11: TMP-019; TMP-020
A12: FR-011 | B12: BR-007 | C12: Audit each task attempt with run/task identity, timing, status, counts, issues, and error details. | D12: Databricks job/task context and module metrics | E12: MERGE STARTED, metrics, SUCCESS/FAILED by run_id + task_run_id. | F12: cibc.gold.pipeline_run_log; valuation_breaks; Silver reject tables | G12: Audit persistence failure fails the task; audit currently omits insert/update/delete/rejects_written counters. | H12: Capture exception type/message; if audit write itself fails log secondary exception. | I12: Success and failure paths produce expected audit record; sensitive exception content reviewed before prod. | J12: trade_pipeline/audit.py; break_report.py; report notebook | K12: PARTIALLY IMPLEMENTED | L12: TMP-019; TMP-024
... A14: FR-013 | B14: BR-008 | C14: Make reruns deterministic and recoverable for a fixed source snapshot and date range. | D14: Same trade snapshot, ticker/date request, run parameters | E14: Trade Bronze overwrite; price/Silver/Gold conditional MERGEs; reject/break writes are idempotent per identity/run. | F14: Stable business keys/values and separate run audit history | G14: A retry gets task attempt identity; full-history recompute is used; no partial input may delete outside source scope. | H14: Fail-fast at bad input; inspect audit/reject/breaks, repair source, rerun; exact operational recovery time TBD. | I14: Two complete identical end-to-end runs preserve business output and business keys; audit history records both. | J14: Ingestion/processing modules; Databricks Workflow; audit | K14: PARTIALLY IMPLEMENTED | L14: TMP-016; TMP-022; TMP-024

Sheet NFRs
A1: NFR ID | B1: Quality attribute | C1: Acceptance target | D1: Status | E1: Evidence / gap
A2: NFR-01 | B2: Performance | C2: PROPOSED: process the documented 1,200-trade / 10-symbol demonstration workload within 15 minutes end-to-end, excluding provider outages. | D2: TO BE CONFIRMED | E2: No measured run duration/SLA recorded in docs/test_results.md.
A3: NFR-02 | B3: Reliability | C3: PROPOSED: >=99% successful scheduled runs per calendar month after production support and alerting are established. | D3: TO BE CONFIRMED | E3: Only a dev job is configured; schedule paused.
A4: NFR-03 | B4: Idempotency | C4: PROPOSED: two runs over identical inputs produce identical business keys and financial values; only run-level audit/break history may grow. | D4: PARTIALLY IMPLEMENTED | E4: Unit tests cover scoped writes; documented second Databricks run was queued, not verified.
A5: NFR-04 | B5: Security | C5: PROPOSED: job service principal has least privilege on cibc schemas and input Volume; secrets never stored in source control; access reviewed before non-dev deploy. | D5: TO BE CONFIRMED | E5: Grant template exists; principal/environment are placeholders.
A6: NFR-05 | B6: Maintainability | C6: PROPOSED: source modules remain separated by Bronze/Silver/Gold; new business rules have unit tests and documented owners. | D6: PARTIALLY IMPLEMENTED | E6: Layered Python package and tests exist; CI/ownership not evidenced.
A7: NFR-06 | B7: Testability | C7: PROPOSED: deterministic unit tests for rules; Spark integration tests for MERGE/Delta behavior; UAT evidence for financial outputs. | D7: PARTIALLY IMPLEMENTED | E7: pytest tests exist; PySpark/Java/Delta runtime availability is not confirmed locally.
A8: NFR-07 | B8: Scalability | C8: PROPOSED: benchmark 100,000 trades and 50 symbols; confirm runtime and compute cost before adopting an incremental design. | D8: TO BE CONFIRMED | E8: Full-history recompute is documented as a prototype limitation; no benchmark.
A9: NFR-08 | B9: Observability | C9: PROPOSED: detect failed run and notify support within 5 minutes; audit every task attempt; reconcile expected task count. | D9: PARTIALLY IMPLEMENTED | E9: Delta audit/reject/break data and report notebook; no automated alerting.
A10: NFR-09 | B10: Deployability | C10: PROPOSED: repeatable Bundle validate/deploy in isolated dev/test/prod targets with reviewable configuration and smoke test. | D10: PARTIALLY IMPLEMENTED | E10: Databricks Asset Bundle has dev target and deploy script; no CI or non-dev target.
A11: NFR-10 | B11: Retention and recovery | C11: TBD by data owner: approve retention, RTO, RPO, and source replay window before production. No numeric policy is assumed. | D11: TO BE CONFIRMED | E11: Not specified in repository.

Sheet Data Sources
A1: Source ID | B1: Source | C1: Status | D1: System/provider | E1: Format/interface | F1: Location | G1: Frequency | H1: Volume | I1: Business key | J1: Version/correction | K1: Quality rules | L1: Ingestion strategy | M1: Failure handling | N1: Open decisions
A2: SRC-TRADE | B2: Trade transactions | C2: IMPLEMENTED (synthetic prototype source) | D2: scripts/generate_trades.py; no upstream trade system integration evidenced | E2: CSV, 14 named columns; raw values landed as STRING | F2: Local data/dirty_trades.csv then /Volumes/cibc/bronze/trade_files/dirty_trades.csv | G2: Full snapshot per Job run; weekday schedule configured but paused; file delivery SLA TBD | H2: Checked-in sample has 1,200 generated rows per docs/test_results.md; production volumes TBD | I2: trade_id is logical entity; version + modified_timestamp select the latest; Bronze has no enforced PK | J2: Highest version, then latest modified_timestamp; invalid/ambiguous latest is not replaced by older version | K2: Nonblank IDs; configured instrument/symbol match; BUY/SELL; nonzero quantity; positive price; USD; valid timestamps/dates; supported NYSE session; settlement next session; version > 0 | L2: Validate exact header/nonempty/structure; dedupe identical in-batch rows; INSERT OVERWRITE Bronze snapshot | M2: Fail before overwrite; audit failure; Silver quarantines business-invalid rows | N2: Real source owner, legal entity/system, delivery format contract, completeness watermark, file naming, correction/deletion semantics, volume/SLA, retention and access classification.
A3: SRC-PRICE | B3: Daily market prices | C3: IMPLEMENTED (prototype provider; not approved for banking production) | D3: Yahoo Finance via yfinance.download; provider rights/approval unverified | E3: Python provider response normalized to symbol, price_date, close, currency | F3: Provider response to cibc.bronze.market_prices Delta | G3: Daily interval; seven-day default lookback; schedule is paused | H3: 10 hard-coded default tickers; volume/limits and broader universe TBD | I3: symbol + price_date (logical business key) | J3: Latest ingestion_timestamp then run_id; conflicting tied payloads rejected | K3: Expected NYSE sessions; non-future date; finite positive close; USD; unique symbol/date; completeness required | L3: Retry up to three attempts; unadjusted Close; Bronze conditional MERGE | M3: No data/omitted symbol/expected missing session fails; no stale close substituted for position valuation | N3: Market-data owner/provider approval and license, adjustment/close definition, correction policy, availability SLA, symbol mapping, market calendar and missing-data escalation.
A4: SRC-REF | B4: Minimal reference data | C4: PARTIALLY IMPLEMENTED (in-code mappings only) | D4: trade_pipeline/config.py INSTRUMENT_ID_TO_SYMBOL; books/counterparties arrive as input strings | E4: Python dictionary and input attributes; no reference Delta tables | F4: Code configuration; no independent reference-data store | G4: Release-time mapping update; business owner/update cadence TBD | H4: 10 configured instrument-symbol pairs; book/counterparty cardinalities unknown | I4: instrument_id; symbol mapping; book_id and counterparty_id are opaque strings | J4: No effective-dated reference history | K4: Configured instrument/symbol match; book/counterparty nonblank; USD-only currency | L4: No separate pipeline; Silver validates against configured mapping | M4: Unknown/mismatched instrument is rejected | N4: Reference-data ownership, effective dating, books/counterparties validation, and need for persisted mappings must be confirmed.

Sheet Data Dictionary
A1: Catalog | B1: Schema | C1: Table | D1: Table purpose | E1: Grain | F1: Business/unique key assumption | G1: Column | H1: Databricks SQL type | I1: Precision/scale | J1: Nullable | K1: Default | L1: Description | M1: Source field | N1: Transformation | O1: Data quality rule | P1: Storage strategy | Q1: Write semantics | R1: DDL file
A2: cibc | B2: bronze | C2: market_prices | D2: Raw price records | E2: One symbol and price date | F2: Logical: symbol + price_date; no enforced constraint | G2: symbol | H2: STRING | I2: N/A | J2: Yes | K2: None declared | L2: Market ticker symbol | M2: CSV.symbol or configured instrument mapping | N2: Normalized/validated against instrument map | O2: Required; mapped and consistent | P2: No physical PK/partition/clustering | Q2: Conditional MERGE on symbol + price_date | R2: database/tables/bronze/market_prices.sql
A3: cibc | B3: bronze | C3: market_prices | D3: Raw price records | E3: One symbol and price date | F3: Logical: symbol + price_date; no enforced constraint | G3: price_date | H3: STRING | I3: N/A | J3: Yes | K3: None declared | L3: Market price effective date | M3: Provider date | N3: try_cast to DATE | O3: Expected supported session; not future | P3: No physical PK/partition/clustering | Q3: Conditional MERGE on symbol + price_date | R3: database/tables/bronze/market_prices.sql
A4: cibc | B4: bronze | C4: market_prices | D4: Raw price records | E4: One symbol and price date | F4: Logical: symbol + price_date; no enforced constraint | G4: close | H4: STRING | I4: N/A | J4: Yes | K4: None declared | L4: Unadjusted daily closing price | M4: Provider Close | N4: try_cast to DECIMAL(18,6) | O4: Required, finite, positive; currency USD | P4: No physical PK/partition/clustering | Q4: Conditional MERGE on symbol + price_date | R4: database/tables/bronze/market_prices.sql
A5: cibc | B5: bronze | C5: market_prices | D5: Raw price records | E5: One symbol and price date | F5: Logical: symbol + price_date; no enforced constraint | G5: currency | H5: STRING | I5: N/A | J5: Yes | K5: None declared | L5: Financial reporting currency | M5: Trade/price source | N5: USD-only prototype | O5: Required on core accepted/Gold data | P5: No physical PK/partition/clustering | Q5: Conditional MERGE on symbol + price_date | R5: database/tables/bronze/market_prices.sql
A6: cibc | B6: bronze | C6: market_prices | D6: Raw price records | E6: One symbol and price date | F6: Logical: symbol + price_date; no enforced constraint | G6: source_api | H6: STRING | I6: N/A | J6: Yes | K6: None declared | L6: Price provider identifier | M6: yfinance.download | N6: Added by price adapter | O6: Provider identity recorded; approved source TBD | P6: No physical PK/partition/clustering | Q6: Conditional MERGE on symbol + price_date | R6: database/tables/bronze/market_prices.sql
A7: cibc | B7: bronze | C7: market_prices | D7: Raw price records | E7: One symbol and price date | F7: Logical: symbol + price_date; no enforced constraint | G7: ingestion_timestamp | H7: TIMESTAMP | I7: N/A | J7: Yes | K7: None declared | L7: Ingestion event timestamp | M7: Pipeline runtime | N7: current_timestamp or provider batch timestamp | O7: Audit lineage | P7: No physical PK/partition/clustering | Q7: Conditional MERGE on symbol + price_date | R7: database/tables/bronze/market_prices.sql
A8: cibc | B8: bronze | C8: market_prices | D8: Raw price records | E8: One symbol and price date | F8: Logical: symbol + price_date; no enforced constraint | G8: run_id | H8: STRING | I8: N/A | J8: Yes | K8: None declared | L8: Pipeline run identifier | M8: Databricks Job run id | N8: Passed to task and persisted | O8: Required for lineage where source available | P8: No physical PK/partition/clustering | Q8: Conditional MERGE on symbol + price_date | R8: database/tables/bronze/market_prices.sql
A9: cibc | B9: bronze | C9: trades | D9: Raw latest trade CSV snapshot | E9: One distinct source row per current file snapshot | F9: No enforced key; source identity is trade fields + version | G9: trade_id | H9: STRING | I9: N/A | J9: Yes | K9: None declared | L9: Trade identifier on valuation break | M9: Silver trade | N9: Nullable for instrument/date-level break | O9: Nullable | P9: No physical PK/partition/clustering; small prototype | Q9: INSERT OVERWRITE after structural validation | R9: database/tables/bronze/trades.sql
A10: cibc | B10: bronze | C10: trades | D10: Raw latest trade CSV snapshot | E10: One distinct source row per current file snapshot | F10: No enforced key; source identity is trade fields + version | G10: counterparty_id | H10: STRING | I10: N/A | J10: Yes | K10: None declared | L10: Counterparty identifier | M10: CSV.counterparty_id | N10: Preserved as STRING | O10: Required/nonblank for accepted trade | P10: No physical PK/partition/clustering; small prototype | Q10: INSERT OVERWRITE after structural validation | R10: database/tables/bronze/trades.sql
A11: cibc | B11: bronze | C11: trades | D11: Raw latest trade CSV snapshot | E11: One distinct source row per current file snapshot | F11: No enforced key; source identity is trade fields + version | G11: instrument_id | H11: STRING | I11: N/A | J11: Yes | K11: None declared | L11: Instrument identifier on position/break | M11: Configured mapping or Silver trade | N11: STRING | O11: Required on accepted trade; nullable in break DDL | P11: No physical PK/partition/clustering; small prototype | Q11: INSERT OVERWRITE after structural validation | R11: database/tables/bronze/trades.sql
A12: cibc | B12: bronze | C12: trades | D12: Raw latest trade CSV snapshot | E12: One distinct source row per current file snapshot | F12: No enforced key; source identity is trade fields + version | G12: symbol | H12: STRING | I12: N/A | J12: Yes | K12: None declared | L12: Market ticker symbol | M12: CSV.symbol or configured instrument mapping | N12: Normalized/validated against instrument map | O12: Required; mapped and consistent | P12: No physical PK/partition/clustering; small prototype | Q12: INSERT OVERWRITE after structural validation | R12: database/tables/bronze/trades.sql
... A139: cibc | B139: silver | C139: trades_rejects | D139: Trade data-quality and version rejects | E139: One rejected raw record/reason history row | F139: Logical reject key from business columns + source file + reason | G139: rejected_at | H139: TIMESTAMP | I139: N/A | J139: Yes | K139: None declared | L139: Reject capture timestamp | M139: Silver processor runtime | N139: current_timestamp | O139: Required for reject record | P139: No physical PK/partition/clustering | Q139: Insert-once MERGE reject history | R139: database/tables/silver/trades_rejects.sql

Sheet Epics
A1: Planning ID | B1: Epic name | C1: Priority | D1: Jira status | E1: Scope note
A2: TMP-EP01 | B2: Project Initiation and Business Analysis | C2: High | D2: To Do | E2: Planning epic; mixed current-state evidence and target backlog. See linked story implementation status.
A3: TMP-EP02 | B3: Requirements and Acceptance Criteria | C3: High | D3: To Do | E3: Planning epic; mixed current-state evidence and target backlog. See linked story implementation status.
A4: TMP-EP03 | B4: Solution Architecture and Technical Design | C4: High | D4: To Do | E4: Planning epic; mixed current-state evidence and target backlog. See linked story implementation status.
A5: TMP-EP04 | B5: Data Sourcing and Data Modelling | C5: High | D5: To Do | E5: Planning epic; mixed current-state evidence and target backlog. See linked story implementation status.
A6: TMP-EP05 | B6: Platform Setup and CI/CD | C6: High | D6: To Do | E6: Planning epic; mixed current-state evidence and target backlog. See linked story implementation status.
A7: TMP-EP06 | B7: Trade Data Ingestion | C7: High | D7: To Do | E7: Planning epic; mixed current-state evidence and target backlog. See linked story implementation status.
A8: TMP-EP07 | B8: Market Price Ingestion | C8: High | D8: To Do | E8: Planning epic; mixed current-state evidence and target backlog. See linked story implementation status.
A9: TMP-EP08 | B9: Silver Data Processing | C9: High | D9: To Do | E9: Planning epic; mixed current-state evidence and target backlog. See linked story implementation status.
A10: TMP-EP09 | B10: Position Calculation | C10: High | D10: To Do | E10: Planning epic; mixed current-state evidence and target backlog. See linked story implementation status.
A11: TMP-EP10 | B11: P&L Calculation | C11: High | D11: To Do | E11: Planning epic; mixed current-state evidence and target backlog. See linked story implementation status.
A12: TMP-EP11 | B12: Reporting and Dashboard | C12: Medium | D12: To Do | E12: Planning epic; mixed current-state evidence and target backlog. See linked story implementation status.
... A14: TMP-EP13 | B14: Deployment, Monitoring and Handover | C14: High | D14: To Do | E14: Planning epic; mixed current-state evidence and target backlog. See linked story implementation status.

Sheet Stories
A1: Planning ID | B1: Epic ID | C1: Story title | D1: User story / objective | E1: Detailed description | F1: Acceptance criteria | G1: Story points | H1: Priority | I1: Implementation status | J1: Sprint | K1: BR IDs | L1: FR IDs | M1: Predecessor stories | N1: Required inputs | O1: Expected outputs
A2: TMP-001 | B2: TMP-EP01 | C2: Baseline current implementation and confirm scope | D2: Record verified capabilities, limitations, stakeholders, assumptions, and prototype-versus-production boundaries. | E2: Use repository modules, DDL, tests, Bundle, and dated run evidence to approve the first scope baseline. Do not describe proposed controls as deployed. | F2: Inventory covers all six workflow tasks, 10 physical tables, two notebooks, Bundle targets, and test evidence.; Every capability is labelled implemented, partial, planned, or to be confirmed with a repository evidence reference.; Business owner confirms prototype scope and named decision owners before Sprint 2 exit. | G2: 2 | H2: High | I2: PARTIALLY IMPLEMENTED | J2: Sprint 1 | K2: BR-001; BR-008 | L2: FR-012 | N2: Repository; product/operations contacts | O2: Approved scope and implementation inventory
A3: TMP-002 | B3: TMP-EP02 | C3: Approve business and functional requirements | D3: Turn current capabilities and business needs into testable BR/FR acceptance criteria. | E3: Confirm user roles, daily business outputs, timing, correction semantics, report needs, and sign-off owners. Link BR-001..008 to FR-001..013. | F3: All eight business requirements have an owner, priority, acceptance evidence, and dependency.; All 13 functional requirements identify input, processing, output, business rule, and failure behavior.; Product owner records decisions or explicit TBDs; no unsupported policy is silently assumed. | G3: 3 | H3: High | I3: PLANNED | J3: Sprint 1 | K3: BR-001; BR-002; BR-003; BR-004; BR-005; BR-006; BR-007; BR-008 | L3: FR-001; FR-002; FR-003; FR-004; FR-005; FR-006; FR-007; FR-008; FR-009; FR-010; FR-011; FR-012; FR-013 | M3: TMP-001 | N3: Implementation inventory; business/operations interviews | O3: Signed requirements and acceptance criteria
A4: TMP-003 | B4: TMP-EP02 | C4: Set measurable non-functional and operational targets | D4: Agree performance, availability, support, security, retention, RTO/RPO, and recovery targets. | E4: Use proposed thresholds as discussion points only. Confirm owner, measurement window, and evidence for each target. | F4: NFR-01..10 each has a confirmed target or named owner and due date for TBD.; Performance baseline includes representative row counts, symbols, runtime, and cost.; Retention, access classification, RTO/RPO, support hours, and alert response are approved or explicitly excluded from prototype. | G4: 2 | H4: High | I4: PLANNED | J4: Sprint 1 | K4: BR-007; BR-008 | L4: FR-011; FR-012; FR-013 | M4: TMP-002 | N4: Business/technology policy owners; proposed NFRs | O4: Approved NFR baseline
A5: TMP-004 | B5: TMP-EP03 | C5: Document and validate existing solution architecture | D5: Establish an evidence-backed architecture baseline and component responsibilities. | E5: Document Unity Catalog, Delta layers, Python wheel, Job, notebooks, audit/rejects, and current deployment path. | F5: Current architecture matches databricks.yml, job YAML, source modules, and DDL.; Trade/price parallel branches and join dependencies are accurate.; Current provider, paused schedule, dev-only target, and notebook reporting are labelled as implemented/current limitations. | G5: 3 | H5: High | I5: IMPLEMENTED | K5: BR-001; BR-002; BR-004; BR-005; BR-007; BR-008 | L5: FR-006; FR-008; FR-011; FR-012 | N5: Repository implementation | O5: Current-state architecture
A6: TMP-005 | B6: TMP-EP03 | C6: Approve target security and environment architecture | D6: Define deployable dev/test/prod boundaries and least-privilege runtime identity. | E6: Design only what is supported by actual workspace controls; confirm environment availability, principals, grants, networking, and secrets approach. | F6: Environment promotion and job identity are approved by platform owner.; Unity Catalog grants cover required schemas and Volume only; no secrets are committed.; Architecture labels all unprovisioned targets and controls as proposed. | G6: 3 | H6: High | I6: PLANNED | J6: Sprint 1 | K6: BR-007; BR-008 | L6: FR-011; FR-012 | M6: TMP-002; TMP-003; TMP-004 | N6: Workspace/platform/security owner decisions | O6: Approved environment and access design
A7: TMP-006 | B7: TMP-EP04 | C7: Confirm trade source contract and snapshot semantics | D7: Make source ownership, completeness, corrections, and deletion semantics explicit. | E7: Current input is synthetic; define the future producer contract and safe transition from full snapshot to an authoritative feed. | F7: Trade source owner, file schema, delivery cutoff, completeness marker, and correction/deletion semantics are recorded.; A missing trade in a later snapshot is not treated as a cancellation without explicit business rule.; Sample volume, retention, privacy classification, and replay window are approved or tracked as TBD. | G7: 2 | H7: High | I7: PARTIALLY IMPLEMENTED | K7: BR-001; BR-003 | L7: FR-001; FR-004; FR-009 | N7: Synthetic CSV; trade owner | O7: Trade source specification
A8: TMP-007 | B8: TMP-EP04 | C8: Select and approve market-data source | D8: Resolve whether Yahoo Finance is acceptable for the prototype and choose a licensed production source. | E8: Confirm price type, currency, adjustments, symbol universe, rights, correction policy, availability, and missing-price escalation; synthetic fixtures are acceptable for deterministic tests only. | F8: Provider and business owner approve data rights and use case before production.; Price-date/price-type/currency contract and correction policy are documented.; Daily availability and expected-session completeness thresholds have named owners. | G8: 3 | H8: High | I8: PLANNED | J8: Sprint 2 | K8: BR-002; BR-005 | L8: FR-002; FR-005; FR-007; FR-008 | M8: TMP-002 | N8: Current yfinance adapter; market-data owner | O8: Approved source decision and interface contract
A9: TMP-008 | B9: TMP-EP04 | C9: Approve physical data dictionary and retention model | D9: Review all current table grains, keys, financial types, lineage, and future retention needs. | E9: Use the 10 physical DDL files as current-state truth; identify no enforced primary keys and no dedicated reference/reporting tables. | F9: Data dictionary lists every column and exact DDL type/nullability for all 10 tables.; Business owner approves table grain and logical key assumptions.; Partitioning/clustering remains absent unless measured query patterns justify it.; Retention and Delta cleanup policy are approved before any production purge/optimization. | G9: 2 | H9: High | I9: PARTIALLY IMPLEMENTED | J9: Sprint 2 | K9: BR-003; BR-004; BR-005; BR-007 | L9: FR-003; FR-006; FR-007; FR-008; FR-009; FR-011 | M9: TMP-006; TMP-007 | N9: database/tables DDL; provider/trade contracts | O9: Approved dictionary and data-retention decisions
A10: TMP-009 | B10: TMP-EP05 | C10: Maintain reproducible Databricks Asset Bundle development deployment | D10: Validate current development Bundle build and deploy path. | E10: Bundle builds a wheel and deploys the six-task job/notebooks to the dev target; schedule remains paused by configuration. | F10: Bundle validation succeeds with the documented dev target and CLI profile.; Wheel contains all six entry points and deploy uses repository source.; Manual smoke run evidence is attached; no production readiness is inferred. | G10: 3 | H10: High | I10: IMPLEMENTED | K10: BR-008 | L10: FR-012 | N10: databricks.yml; job resource; scripts/deploy.sh | O10: Validated dev deployment procedure
A11: TMP-010 | B11: TMP-EP05 | C11: Add reviewed CI checks and controlled deployment promotion | D11: Automate deterministic tests, Bundle validation, and reviewed artifact promotion. | E11: Create CI using existing pytest/package/Bundle checks; add non-dev targets only after platform provisioning and identity approval. | F11: Pull request CI runs deterministic local tests and Bundle validation without credentials in logs.; Deployment artifact/version is traceable to reviewed source revision.; Promotion cannot unpause a schedule or deploy to an unapproved target without explicit approval. | G11: 5 | H11: High | I11: PLANNED | J11: Sprint 3 | K11: BR-007; BR-008 | L11: FR-012; FR-013 | M11: TMP-005; TMP-009 | N11: Approved environment/security design; current Bundle | O11: CI workflow and controlled deploy procedure
A12: TMP-011 | B12: TMP-EP06 | C12: Ingest synthetic trade snapshot into Bronze | D12: Load structurally valid trade snapshots with deterministic raw lineage. | E12: Current implementation validates the 14-field CSV and atomically overwrites Bronze after input checks. | F12: Exact schema, empty-file, and malformed-row cases are tested.; Identical in-batch records are removed; versions of a trade remain present.; Invalid file never overwrites existing Bronze; valid rerun yields same business rows. | G12: 5 | H12: High | I12: IMPLEMENTED | K12: BR-001; BR-003 | L12: FR-001; FR-013 | M12: TMP-006 | N12: CSV snapshot in UC Volume | O12: cibc.bronze.trades
A13: TMP-012 | B13: TMP-EP06 | C13: Resolve trade snapshot disappearance and historical correction controls | D13: Prevent a source snapshot replacement from leaving stale or silently deleting trades. | E13: Current Bronze retains only latest snapshot and Silver does not remove trade IDs absent from a later file. Choose event/history storage or safe snapshot reconciliation. | F13: Trade owner approves semantics for missing trade IDs, cancellation, and correction.; A two-snapshot test proves accepted Silver matches the agreed authoritative source state.; Backdated corrections are traceable and recompute the intended history without unrelated deletes. | G13: 5 | H13: High | I13: PLANNED | J13: Sprint 3 | K13: BR-003; BR-004; BR-005 | L13: FR-004; FR-009; FR-013 | M13: TMP-006; TMP-011 | N13: Approved trade source semantics; current Bronze/Silver behavior | O13: Versioned history/reconciliation design and tested implementation
A14: TMP-013 | B14: TMP-EP07 | C14: Ingest and retain daily market-price history | D14: Load supported daily close records with source identity and repeatable keys. | E14: Current adapter calls Yahoo Finance, stores unadjusted closes, retries transient failures, and merges Bronze on symbol/date. | F14: Default symbols, date boundaries, provider response variants, NaN, duplicate keys, and retry errors have deterministic tests.; Price rows carry source, currency, ingestion timestamp, and run lineage.; Provider limitations and data rights are explicit in the source contract. | G14: 5 | H14: High | I14: IMPLEMENTED | K14: BR-002 | L14: FR-002; FR-013 | M14: TMP-007 | N14: Daily price provider response | O14: cibc.bronze.market_prices
A15: TMP-014 | B15: TMP-EP07 | C15: Harden price source decision and completeness exception process | D15: Make price completeness and manual resolution operationally actionable. | E15: Use provider choice from TMP-007; define approved synthetic fixtures for test environments and operational handling for late/missing prices. | F15: Missing expected session is tied to symbol/date and owner; no stale price is used for position valuation.; Test fixtures are deterministic and cannot be mistaken for production source data.; Approved provider/credentials, rate limits, correction policy, and retries are configured outside source code where required. | G15: 3 | H15: High | I15: PLANNED | J15: Sprint 2 | K15: BR-002; BR-005; BR-007 | L15: FR-002; FR-005; FR-007; FR-013 | M15: TMP-007; TMP-013 | N15: Approved provider decision; current completeness checks | O15: Price-source controls and exception runbook
A16: TMP-015 | B16: TMP-EP08 | C16: Validate Silver trades and prices with reject history | D16: Publish typed records only after business validation and deterministic version selection. | E16: Current code performs typed conversion, configured business checks, deduplication/versioning, conditional merge, and reject-history writes. | F16: Trade and price fixtures cover configured rules and reason codes.; Silver trade business key is trade_id; price key is symbol + price_date.; Reject writes are idempotent and preserve raw source fields/lineage; missing expected price blocks Silver update. | G16: 5 | H16: High | I16: IMPLEMENTED | K16: BR-003; BR-007 | L16: FR-003; FR-004; FR-005; FR-013 | M16: TMP-011; TMP-013 | N16: Bronze trades and prices | O16: Silver validated tables and rejects
A17: TMP-016 | B17: TMP-EP08 | C17: Run Spark/Delta integration and end-to-end rerun validation | D17: Prove Delta writes, constraints, lineage, recovery, and same-input idempotency in a supported runtime. | E17: Local Spark availability is not evidenced; docs/test_results.md records a successful dated pipeline run but its same-parameter second run was queued. | F17: Spark/Delta integration suite runs in a supported CI or Databricks test environment and results are retained.; A second complete run with the same inputs verifies stable business keys/values and expected audit history growth.; Failure injection confirms no unsafe publication and a documented rerun recovers the task. | G17: 2 | H17: High | I17: PLANNED | J17: Sprint 2 | K17: BR-003; BR-007; BR-008 | L17: FR-003; FR-005; FR-009; FR-013 | M17: TMP-015 | N17: Supported Spark/Delta environment; current test suite | O17: Integration, idempotency, and recovery evidence
A18: TMP-017 | B18: TMP-EP09 | C18: Build cumulative daily positions and exact-date valuation | D18: Publish historical positions at the agreed book/counterparty/instrument/date grain. | E18: Current implementation aggregates signed trade quantities, carries positions across trading sessions, and joins same-day same-currency marks. | F18: Position grain and key match the approved dictionary.; Daily buys, sells, net, closing quantity, close, and market value reconcile to independent calculations.; Missing same-day price leaves price/value NULL and creates a break without changing quantity. | G18: 5 | H18: High | I18: IMPLEMENTED | K18: BR-004; BR-005 | L18: FR-006; FR-007; FR-009 | M18: TMP-015 | N18: Silver trades and prices | O18: cibc.gold.positions; position valuation breaks
A19: TMP-018 | B19: TMP-EP10 | C19: Calculate daily cash-equity mark-to-market P&L | D19: Separate opening position market move from trade-day economic P&L. | E19: Current Gold formula uses prior close for opening inventory and signed trade consideration for intraday activity; cumulative proxy is not true unrealized P&L. | F19: Daily output grain is valuation_date + book_id + symbol + currency.; Price movement and trade-day terms reconcile independently, including sells, new/flat positions, prior-close baseline, and missing prices.; unrealized_pnl_proxy is clearly labelled as a cumulative proxy and is not presented as true unrealized P&L. | G19: 5 | H19: High | I19: IMPLEMENTED | K19: BR-005 | L19: FR-007; FR-008; FR-009 | M19: TMP-017 | N19: Gold positions; Silver trades/prices | O19: cibc.gold.daily_pnl; P&L breaks
A20: TMP-019 | B20: TMP-EP11 | C20: Provide notebook and SQL operational reporting | D20: Expose current job run, audit metrics, rejections, positions, P&L, and valuation breaks. | E20: A run-trigger notebook, read-only report notebook, and demo SQL exist. No deployed dashboard is evidenced. | F20: Run report identifies audit-derived status and clearly marks unavailable counts.; Notebook output is read-only and totals reconcile to source tables.; Report states that scheduled-run completeness is not evaluated and dashboard is not implemented. | G20: 3 | H20: Medium | I20: IMPLEMENTED | K20: BR-006; BR-007; BR-008 | L20: FR-010; FR-011; FR-012 | M20: TMP-018 | N20: Gold/Silver tables and Jobs API | O20: Run-control/report notebooks and SQL queries
A21: TMP-020 | B21: TMP-EP11 | C21: Deliver user-accepted trading and P&L dashboard MVP | D21: Present agreed Gold reporting datasets in an approved Databricks SQL dashboard or chosen BI tool. | E21: Dashboard technology, user roles, filters, reconciliation views, and access model remain to be confirmed; this is proposed work, not current functionality. | F21: Product owner signs off audience, filters, date/book/symbol dimensions, and exception drill-through.; Dashboard totals reconcile to Gold daily_pnl and positions for agreed test dates.; Dashboard access is least privilege and deployment is repeatable; no dashboard is reported as live before sign-off. | G21: 5 | H21: Medium | I21: PLANNED | J21: Sprint 4 | K21: BR-006 | L21: FR-010 | M21: TMP-002; TMP-008; TMP-018; TMP-019 | N21: Approved reporting requirements; Gold datasets | O21: Dashboard MVP and validation evidence
A22: TMP-021 | B22: TMP-EP12 | C22: Maintain deterministic unit and transformation tests | D22: Protect module contracts and calculation rules with repeatable test cases. | E22: Tests cover source parsing, transformations, DDL/query shape, packaging, notebook helpers, and financial examples; Spark-dependent cases need a compatible runtime. Three focused tests currently fail because they reference removed Silver *_constraints.sql files; current checks are consolidated into trades.sql and market_prices.sql. | F22: Business-rule tests include correction, duplicate, calendar, missing price, short position, and P&L decomposition cases.; CI reports skips separately from passes and does not treat unavailable Spark tests as verified.; Replace stale test references with the consolidated Silver DDL and verify its CHECK constraints.; New failures are triaged against the baseline; no unrelated failures are silently waived. | G22: 3 | H22: High | I22: PARTIALLY IMPLEMENTED | K22: BR-001; BR-002; BR-003; BR-004; BR-005; BR-007 | L22: FR-001; FR-002; FR-003; FR-004; FR-005; FR-006; FR-007; FR-008 | N22: pytest suite; supported Python/Spark runtime | O22: Deterministic test evidence
A23: TMP-022 | B23: TMP-EP12 | C23: Complete independent position/P&L reconciliation and UAT | D23: Close the gap between pipeline output and business-approved calculations. | E23: The 2026-10-11 run has independent SQL reconciliation with zero reported mismatches; same-input rerun remained queued in the report. | F23: Trade-to-position quantities reconcile by date/book/counterparty/instrument.; Position market value and daily P&L reconcile using approved close/baseline/trade cash-flow methodology.; Business owner signs UAT evidence for representative long, short, flat, correction, and missing-price cases.; A complete same-input rerun has recorded evidence; do not rely only on unit tests. | G23: 2 | H23: High | I23: PARTIALLY IMPLEMENTED | J23: Sprint 4 | K23: BR-003; BR-004; BR-005; BR-006 | L23: FR-006; FR-007; FR-008; FR-009; FR-010; FR-013 | M23: TMP-016; TMP-018 | N23: Gold outputs; independent SQL; business test cases | O23: Reconciliation and UAT sign-off
A24: TMP-023 | B24: TMP-EP13 | C24: Operate the dev workflow with controlled scheduling | D24: Use existing Asset Bundle workflow safely and keep schedule gated on readiness. | E24: Current Job allows one concurrent run, runs six tasks, and has a weekday 18:00 America/New_York schedule configured as PAUSED. | F24: Manual run and failure states are visible in Job UI and audit tables.; Schedule remains paused until source owner, support contact, permissions, runbook, and alert path are approved.; Any future unpause/change is reviewed and recorded with owner and rollback path. | G24: 3 | H24: High | I24: PARTIALLY IMPLEMENTED | K24: BR-007; BR-008 | L24: FR-011; FR-012; FR-013 | M24: TMP-009 | N24: Deployed dev Job; operational readiness decisions | O24: Controlled dev operating procedure
A25: TMP-024 | B25: TMP-EP13 | C25: Create support runbook, alerting, and handover | D25: Prepare an operational handoff with actionable diagnosis and escalation. | E25: Define monitoring on Job/audit/reject/break signals; alerting and support ownership are not implemented in the repo. | F25: Runbook describes failed task diagnosis, source repair, safe rerun, reconciliation, and escalation owner.; Alert criteria and response targets are approved and tested; proposed five-minute detection target remains proposed until measured.; Handover includes architecture, data contracts, access, known limitations, deployment procedure, and open risks. | G25: 3 | H25: High | I25: PLANNED | J25: Sprint 4 | K25: BR-007; BR-008 | L25: FR-011; FR-012; FR-013 | M25: TMP-003; TMP-019; TMP-022; TMP-023 | N25: Approved NFRs; report; reconciliation; support contacts | O25: Runbook, notification path, handover sign-off

Sheet Subtasks
A1: Subtask ID | B1: Parent story | C1: Description | D1: Expected output | E1: Dependency
A2: TMP-001-ST01 | B2: TMP-001 | C2: Inventory code, DDL, tests, docs, and deployment assets | D2: Completed evidence for inventory code, ddl, tests, docs, and deployment assets | E2: Parent story and its predecessors
A3: TMP-001-ST02 | B3: TMP-001 | C3: Review prototype boundaries and obtain scope decisions | D3: Completed evidence for review prototype boundaries and obtain scope decisions | E3: Parent story and its predecessors
A4: TMP-002-ST01 | B4: TMP-002 | C4: Interview trading, operations, and technology stakeholders | D4: Completed evidence for interview trading, operations, and technology stakeholders | E4: Parent story and its predecessors
A5: TMP-002-ST02 | B5: TMP-002 | C5: Review and approve BR/FR traceability and decisions | D5: Completed evidence for review and approve br/fr traceability and decisions | E5: Parent story and its predecessors
A6: TMP-003-ST01 | B6: TMP-003 | C6: Measure demo workload and propose service thresholds | D6: Completed evidence for measure demo workload and propose service thresholds | E6: Parent story and its predecessors
A7: TMP-003-ST02 | B7: TMP-003 | C7: Confirm security, retention, recovery, and support policies | D7: Completed evidence for confirm security, retention, recovery, and support policies | E7: Parent story and its predecessors
A8: TMP-004-ST01 | B8: TMP-004 | C8: Trace workflow and component ownership from code/config | D8: Completed evidence for trace workflow and component ownership from code/config | E8: Parent story and its predecessors
A9: TMP-004-ST02 | B9: TMP-004 | C9: Review target-state gap and architecture decisions | D9: Completed evidence for review target-state gap and architecture decisions | E9: Parent story and its predecessors
A10: TMP-005-ST01 | B10: TMP-005 | C10: Confirm target workspaces, principals, and data access | D10: Completed evidence for confirm target workspaces, principals, and data access | E10: Parent story and its predecessors
A11: TMP-005-ST02 | B11: TMP-005 | C11: Document secret, grant, and deployment configuration controls | D11: Completed evidence for document secret, grant, and deployment configuration controls | E11: Parent story and its predecessors
A12: TMP-006-ST01 | B12: TMP-006 | C12: Confirm 14-column schema and required fields | D12: Completed evidence for confirm 14-column schema and required fields | E12: Parent story and its predecessors
... A49: TMP-024-ST02 | B49: TMP-024 | C49: Write recovery/runbook and conduct handover walkthrough | D49: Completed evidence for write recovery/runbook and conduct handover walkthrough | E49: Parent story and its predecessors

Sheet Acceptance Criteria
A1: Story ID | B1: Story title | C1: AC # | D1: Testable acceptance criterion
A2: TMP-001 | B2: Baseline current implementation and confirm scope | C2: 1 | D2: Inventory covers all six workflow tasks, 10 physical tables, two notebooks, Bundle targets, and test evidence.
A3: TMP-001 | B3: Baseline current implementation and confirm scope | C3: 2 | D3: Every capability is labelled implemented, partial, planned, or to be confirmed with a repository evidence reference.
A4: TMP-001 | B4: Baseline current implementation and confirm scope | C4: 3 | D4: Business owner confirms prototype scope and named decision owners before Sprint 2 exit.
A5: TMP-002 | B5: Approve business and functional requirements | C5: 1 | D5: All eight business requirements have an owner, priority, acceptance evidence, and dependency.
A6: TMP-002 | B6: Approve business and functional requirements | C6: 2 | D6: All 13 functional requirements identify input, processing, output, business rule, and failure behavior.
A7: TMP-002 | B7: Approve business and functional requirements | C7: 3 | D7: Product owner records decisions or explicit TBDs; no unsupported policy is silently assumed.
A8: TMP-003 | B8: Set measurable non-functional and operational targets | C8: 1 | D8: NFR-01..10 each has a confirmed target or named owner and due date for TBD.
A9: TMP-003 | B9: Set measurable non-functional and operational targets | C9: 2 | D9: Performance baseline includes representative row counts, symbols, runtime, and cost.
A10: TMP-003 | B10: Set measurable non-functional and operational targets | C10: 3 | D10: Retention, access classification, RTO/RPO, support hours, and alert response are approved or explicitly excluded from prototype.
A11: TMP-004 | B11: Document and validate existing solution architecture | C11: 1 | D11: Current architecture matches databricks.yml, job YAML, source modules, and DDL.
A12: TMP-004 | B12: Document and validate existing solution architecture | C12: 2 | D12: Trade/price parallel branches and join dependencies are accurate.
A13: TMP-004 | B13: Document and validate existing solution architecture | C13: 3 | D13: Current provider, paused schedule, dev-only target, and notebook reporting are labelled as implemented/current limitations.
... A76: TMP-024 | B76: Create support runbook, alerting, and handover | C76: 3 | D76: Handover includes architecture, data contracts, access, known limitations, deployment procedure, and open risks.

Sheet Dependencies
A1: Predecessor | B1: Successor | C1: Relationship | D1: Dependency type | E1: Sprint/status | F1: Rationale / expected output
A2: TMP-001 | B2: TMP-002 | C2: blocks | D2: Story delivery dependency | E2: Sprint 1 | F2: Predecessor output required before dependent story acceptance
A3: TMP-002 | B3: TMP-003 | C3: blocks | D3: Story delivery dependency | E3: Sprint 1 | F3: Predecessor output required before dependent story acceptance
A4: TMP-002 | B4: TMP-005 | C4: blocks | D4: Story delivery dependency | E4: Sprint 1 | F4: Predecessor output required before dependent story acceptance
A5: TMP-003 | B5: TMP-005 | C5: blocks | D5: Story delivery dependency | E5: Sprint 1 | F5: Predecessor output required before dependent story acceptance
A6: TMP-004 | B6: TMP-005 | C6: blocks | D6: Story delivery dependency | E6: Sprint 1 | F6: Predecessor output required before dependent story acceptance
A7: TMP-002 | B7: TMP-007 | C7: blocks | D7: Story delivery dependency | E7: Sprint 2 | F7: Predecessor output required before dependent story acceptance
A8: TMP-006 | B8: TMP-008 | C8: blocks | D8: Story delivery dependency | E8: Sprint 2 | F8: Predecessor output required before dependent story acceptance
A9: TMP-007 | B9: TMP-008 | C9: blocks | D9: Story delivery dependency | E9: Sprint 2 | F9: Predecessor output required before dependent story acceptance
A10: TMP-005 | B10: TMP-010 | C10: blocks | D10: Story delivery dependency | E10: Sprint 3 | F10: Predecessor output required before dependent story acceptance
A11: TMP-009 | B11: TMP-010 | C11: blocks | D11: Story delivery dependency | E11: Sprint 3 | F11: Predecessor output required before dependent story acceptance
A12: TMP-006 | B12: TMP-011 | C12: blocks | D12: Story delivery dependency | E12: Current/complete | F12: Predecessor output required before dependent story acceptance
... A39: build_positions | B39: calculate_daily_pnl | C39: blocks | D39: Implemented Databricks Workflow dependency | E39: Current workflow | F39: Verified in jobs/resources/trade_pipeline.job.yml

Sheet Sprints
A1: Sprint | B1: Timeline | C1: Sprint goal | D1: Planned stories | E1: Story points (formula) | F1: Dependencies | G1: Deliverables | H1: Demo outcome | I1: Exit criteria
A2: Sprint 1 | B2: Weeks 1-2 | C2: Lock project scope, requirement acceptance, measurable NFRs, and target access design. | D2: TMP-001; TMP-002; TMP-003; TMP-005 | E2: =SUMIF(Stories!$J:$J,A2,Stories!$G:$G) | F2: Kickoff and timely access to business, market-data, and platform decision owners. | G2: Approved scope, BR/FR baseline, NFR decision log, target security/environment design. | H2: Trace one trade and one price source through implemented modules and show signed acceptance criteria. | I2: No critical source, access, calculation, or report requirement remains ownerless.
A3: Sprint 2 | B3: Weeks 3-4 | C3: Resolve market-data decisions, dictionary, price exception handling, and runtime test strategy. | D3: TMP-007; TMP-008; TMP-014; TMP-016 | E3: =SUMIF(Stories!$J:$J,A3,Stories!$G:$G) | F3: Sprint 1 approved scope; access to market-data owner; supported Databricks/Spark test environment. | G3: Source decision, DDL-backed dictionary signoff, missing-price procedure, integration/rerun evidence. | H3: Show a missing-session case and typed data/reject outcomes; demonstrate integration suite execution. | I3: Price feed is approved or explicitly remains prototype-only; unresolved runtime/test access has an owner and date.
A4: Sprint 3 | B4: Weeks 5-6 | C4: Improve deployment controls and resolve trade snapshot history/correction semantics. | D4: TMP-010; TMP-012 | E4: =SUMIF(Stories!$J:$J,A4,Stories!$G:$G) | F4: Approved security/environment design; trade owner signs source semantics. | G4: Reviewed CI and promotion controls; tested correction/disappearance behavior. | H4: Show PR checks and a two-snapshot correction/cancellation case. | I4: Deployment path is reproducible and trade history behavior is explicit/tested.
A5: Sprint 4 | B5: Weeks 7-8 | C5: Deliver reporting MVP, reconciliation/UAT evidence, and operations handover. | D5: TMP-020; TMP-022; TMP-024 | E5: =SUMIF(Stories!$J:$J,A5,Stories!$G:$G) | F5: Approved reporting requirements, integration evidence, support owner, and prior sprint outputs. | G5: Dashboard MVP, signed UAT/reconciliation, runbook and alerting handover. | H5: Show dashboard reconciliation from source trade through daily P&L and demonstrate failure recovery. | I5: Product/operations sign-off; no unresolved critical risk; schedule stays paused absent production readiness approval.

Sheet Gantt
A1: Planning ID | B1: Story | C1: Sprint | D1: Start week | E1: Duration (weeks) | F1: Week 1 | G1: Week 2 | H1: Week 3 | I1: Week 4 | J1: Week 5 | K1: Week 6 | L1: Week 7 | M1: Week 8
A2: TMP-001 | B2: Baseline current implementation and confirm scope | C2: Sprint 1 | D2: 1 | E2: 2 | F2: =--AND(COLUMN()-5>=$D2,COLUMN()-5<$D2+$E2) | G2: =--AND(COLUMN()-5>=$D2,COLUMN()-5<$D2+$E2) | H2: =--AND(COLUMN()-5>=$D2,COLUMN()-5<$D2+$E2) | I2: =--AND(COLUMN()-5>=$D2,COLUMN()-5<$D2+$E2) | J2: =--AND(COLUMN()-5>=$D2,COLUMN()-5<$D2+$E2) | K2: =--AND(COLUMN()-5>=$D2,COLUMN()-5<$D2+$E2) | L2: =--AND(COLUMN()-5>=$D2,COLUMN()-5<$D2+$E2) | M2: =--AND(COLUMN()-5>=$D2,COLUMN()-5<$D2+$E2)
A3: TMP-002 | B3: Approve business and functional requirements | C3: Sprint 1 | D3: 1 | E3: 2 | F3: =--AND(COLUMN()-5>=$D3,COLUMN()-5<$D3+$E3) | G3: =--AND(COLUMN()-5>=$D3,COLUMN()-5<$D3+$E3) | H3: =--AND(COLUMN()-5>=$D3,COLUMN()-5<$D3+$E3) | I3: =--AND(COLUMN()-5>=$D3,COLUMN()-5<$D3+$E3) | J3: =--AND(COLUMN()-5>=$D3,COLUMN()-5<$D3+$E3) | K3: =--AND(COLUMN()-5>=$D3,COLUMN()-5<$D3+$E3) | L3: =--AND(COLUMN()-5>=$D3,COLUMN()-5<$D3+$E3) | M3: =--AND(COLUMN()-5>=$D3,COLUMN()-5<$D3+$E3)
A4: TMP-003 | B4: Set measurable non-functional and operational targets | C4: Sprint 1 | D4: 1 | E4: 2 | F4: =--AND(COLUMN()-5>=$D4,COLUMN()-5<$D4+$E4) | G4: =--AND(COLUMN()-5>=$D4,COLUMN()-5<$D4+$E4) | H4: =--AND(COLUMN()-5>=$D4,COLUMN()-5<$D4+$E4) | I4: =--AND(COLUMN()-5>=$D4,COLUMN()-5<$D4+$E4) | J4: =--AND(COLUMN()-5>=$D4,COLUMN()-5<$D4+$E4) | K4: =--AND(COLUMN()-5>=$D4,COLUMN()-5<$D4+$E4) | L4: =--AND(COLUMN()-5>=$D4,COLUMN()-5<$D4+$E4) | M4: =--AND(COLUMN()-5>=$D4,COLUMN()-5<$D4+$E4)
A5: TMP-005 | B5: Approve target security and environment architecture | C5: Sprint 1 | D5: 1 | E5: 2 | F5: =--AND(COLUMN()-5>=$D5,COLUMN()-5<$D5+$E5) | G5: =--AND(COLUMN()-5>=$D5,COLUMN()-5<$D5+$E5) | H5: =--AND(COLUMN()-5>=$D5,COLUMN()-5<$D5+$E5) | I5: =--AND(COLUMN()-5>=$D5,COLUMN()-5<$D5+$E5) | J5: =--AND(COLUMN()-5>=$D5,COLUMN()-5<$D5+$E5) | K5: =--AND(COLUMN()-5>=$D5,COLUMN()-5<$D5+$E5) | L5: =--AND(COLUMN()-5>=$D5,COLUMN()-5<$D5+$E5) | M5: =--AND(COLUMN()-5>=$D5,COLUMN()-5<$D5+$E5)
A6: TMP-007 | B6: Select and approve market-data source | C6: Sprint 2 | D6: 3 | E6: 2 | F6: =--AND(COLUMN()-5>=$D6,COLUMN()-5<$D6+$E6) | G6: =--AND(COLUMN()-5>=$D6,COLUMN()-5<$D6+$E6) | H6: =--AND(COLUMN()-5>=$D6,COLUMN()-5<$D6+$E6) | I6: =--AND(COLUMN()-5>=$D6,COLUMN()-5<$D6+$E6) | J6: =--AND(COLUMN()-5>=$D6,COLUMN()-5<$D6+$E6) | K6: =--AND(COLUMN()-5>=$D6,COLUMN()-5<$D6+$E6) | L6: =--AND(COLUMN()-5>=$D6,COLUMN()-5<$D6+$E6) | M6: =--AND(COLUMN()-5>=$D6,COLUMN()-5<$D6+$E6)
A7: TMP-008 | B7: Approve physical data dictionary and retention model | C7: Sprint 2 | D7: 3 | E7: 2 | F7: =--AND(COLUMN()-5>=$D7,COLUMN()-5<$D7+$E7) | G7: =--AND(COLUMN()-5>=$D7,COLUMN()-5<$D7+$E7) | H7: =--AND(COLUMN()-5>=$D7,COLUMN()-5<$D7+$E7) | I7: =--AND(COLUMN()-5>=$D7,COLUMN()-5<$D7+$E7) | J7: =--AND(COLUMN()-5>=$D7,COLUMN()-5<$D7+$E7) | K7: =--AND(COLUMN()-5>=$D7,COLUMN()-5<$D7+$E7) | L7: =--AND(COLUMN()-5>=$D7,COLUMN()-5<$D7+$E7) | M7: =--AND(COLUMN()-5>=$D7,COLUMN()-5<$D7+$E7)
A8: TMP-010 | B8: Add reviewed CI checks and controlled deployment promotion | C8: Sprint 3 | D8: 5 | E8: 2 | F8: =--AND(COLUMN()-5>=$D8,COLUMN()-5<$D8+$E8) | G8: =--AND(COLUMN()-5>=$D8,COLUMN()-5<$D8+$E8) | H8: =--AND(COLUMN()-5>=$D8,COLUMN()-5<$D8+$E8) | I8: =--AND(COLUMN()-5>=$D8,COLUMN()-5<$D8+$E8) | J8: =--AND(COLUMN()-5>=$D8,COLUMN()-5<$D8+$E8) | K8: =--AND(COLUMN()-5>=$D8,COLUMN()-5<$D8+$E8) | L8: =--AND(COLUMN()-5>=$D8,COLUMN()-5<$D8+$E8) | M8: =--AND(COLUMN()-5>=$D8,COLUMN()-5<$D8+$E8)
A9: TMP-012 | B9: Resolve trade snapshot disappearance and historical correction controls | C9: Sprint 3 | D9: 5 | E9: 2 | F9: =--AND(COLUMN()-5>=$D9,COLUMN()-5<$D9+$E9) | G9: =--AND(COLUMN()-5>=$D9,COLUMN()-5<$D9+$E9) | H9: =--AND(COLUMN()-5>=$D9,COLUMN()-5<$D9+$E9) | I9: =--AND(COLUMN()-5>=$D9,COLUMN()-5<$D9+$E9) | J9: =--AND(COLUMN()-5>=$D9,COLUMN()-5<$D9+$E9) | K9: =--AND(COLUMN()-5>=$D9,COLUMN()-5<$D9+$E9) | L9: =--AND(COLUMN()-5>=$D9,COLUMN()-5<$D9+$E9) | M9: =--AND(COLUMN()-5>=$D9,COLUMN()-5<$D9+$E9)
A10: TMP-014 | B10: Harden price source decision and completeness exception process | C10: Sprint 2 | D10: 3 | E10: 2 | F10: =--AND(COLUMN()-5>=$D10,COLUMN()-5<$D10+$E10) | G10: =--AND(COLUMN()-5>=$D10,COLUMN()-5<$D10+$E10) | H10: =--AND(COLUMN()-5>=$D10,COLUMN()-5<$D10+$E10) | I10: =--AND(COLUMN()-5>=$D10,COLUMN()-5<$D10+$E10) | J10: =--AND(COLUMN()-5>=$D10,COLUMN()-5<$D10+$E10) | K10: =--AND(COLUMN()-5>=$D10,COLUMN()-5<$D10+$E10) | L10: =--AND(COLUMN()-5>=$D10,COLUMN()-5<$D10+$E10) | M10: =--AND(COLUMN()-5>=$D10,COLUMN()-5<$D10+$E10)
A11: TMP-016 | B11: Run Spark/Delta integration and end-to-end rerun validation | C11: Sprint 2 | D11: 3 | E11: 2 | F11: =--AND(COLUMN()-5>=$D11,COLUMN()-5<$D11+$E11) | G11: =--AND(COLUMN()-5>=$D11,COLUMN()-5<$D11+$E11) | H11: =--AND(COLUMN()-5>=$D11,COLUMN()-5<$D11+$E11) | I11: =--AND(COLUMN()-5>=$D11,COLUMN()-5<$D11+$E11) | J11: =--AND(COLUMN()-5>=$D11,COLUMN()-5<$D11+$E11) | K11: =--AND(COLUMN()-5>=$D11,COLUMN()-5<$D11+$E11) | L11: =--AND(COLUMN()-5>=$D11,COLUMN()-5<$D11+$E11) | M11: =--AND(COLUMN()-5>=$D11,COLUMN()-5<$D11+$E11)
A12: TMP-020 | B12: Deliver user-accepted trading and P&L dashboard MVP | C12: Sprint 4 | D12: 7 | E12: 2 | F12: =--AND(COLUMN()-5>=$D12,COLUMN()-5<$D12+$E12) | G12: =--AND(COLUMN()-5>=$D12,COLUMN()-5<$D12+$E12) | H12: =--AND(COLUMN()-5>=$D12,COLUMN()-5<$D12+$E12) | I12: =--AND(COLUMN()-5>=$D12,COLUMN()-5<$D12+$E12) | J12: =--AND(COLUMN()-5>=$D12,COLUMN()-5<$D12+$E12) | K12: =--AND(COLUMN()-5>=$D12,COLUMN()-5<$D12+$E12) | L12: =--AND(COLUMN()-5>=$D12,COLUMN()-5<$D12+$E12) | M12: =--AND(COLUMN()-5>=$D12,COLUMN()-5<$D12+$E12)
A13: TMP-022 | B13: Complete independent position/P&L reconciliation and UAT | C13: Sprint 4 | D13: 7 | E13: 2 | F13: =--AND(COLUMN()-5>=$D13,COLUMN()-5<$D13+$E13) | G13: =--AND(COLUMN()-5>=$D13,COLUMN()-5<$D13+$E13) | H13: =--AND(COLUMN()-5>=$D13,COLUMN()-5<$D13+$E13) | I13: =--AND(COLUMN()-5>=$D13,COLUMN()-5<$D13+$E13) | J13: =--AND(COLUMN()-5>=$D13,COLUMN()-5<$D13+$E13) | K13: =--AND(COLUMN()-5>=$D13,COLUMN()-5<$D13+$E13) | L13: =--AND(COLUMN()-5>=$D13,COLUMN()-5<$D13+$E13) | M13: =--AND(COLUMN()-5>=$D13,COLUMN()-5<$D13+$E13)
A14: TMP-024 | B14: Create support runbook, alerting, and handover | C14: Sprint 4 | D14: 7 | E14: 2 | F14: =--AND(COLUMN()-5>=$D14,COLUMN()-5<$D14+$E14) | G14: =--AND(COLUMN()-5>=$D14,COLUMN()-5<$D14+$E14) | H14: =--AND(COLUMN()-5>=$D14,COLUMN()-5<$D14+$E14) | I14: =--AND(COLUMN()-5>=$D14,COLUMN()-5<$D14+$E14) | J14: =--AND(COLUMN()-5>=$D14,COLUMN()-5<$D14+$E14) | K14: =--AND(COLUMN()-5>=$D14,COLUMN()-5<$D14+$E14) | L14: =--AND(COLUMN()-5>=$D14,COLUMN()-5<$D14+$E14) | M14: =--AND(COLUMN()-5>=$D14,COLUMN()-5<$D14+$E14)

Sheet Milestones
A1: Milestone ID | B1: Milestone | C1: Target timing | D1: Evidence | E1: Accountable owner | F1: Exit gate | G1: Status
A2: M-01 | B2: Scope and requirements baseline | C2: End Week 2 | D2: Approved BR/FR, NFRs, RAID owners, target access design | E2: Product Owner / Lead Engineer | F2: Sources, calculation scope, roles, and acceptance evidence agreed | G2: Proposed
A3: M-02 | B3: Source and data design sign-off | C3: End Week 4 | D3: Provider decision, source contracts, dictionary, integration test result | E3: Data Owner / Architect | F3: Provider rights and supported test runtime confirmed or scope explicitly remains prototype | G3: Proposed
A4: M-03 | B4: Engineering controls ready | C4: End Week 6 | D4: CI checks, deployment procedure, trade history reconciliation tests | E4: Lead Engineer | F4: Reviewed build/deploy and correction behavior proven | G4: Proposed
A5: M-04 | B5: Prototype acceptance and handover | C5: End Week 8 | D5: Dashboard UAT, end-to-end reconciliation, runbook, open risk acceptance | E5: Product Owner / Operations | F5: Business and operations sign-off; no schedule unpause without separate production approval | G5: Proposed

Sheet RAID
A1: RAID ID | B1: Type | C1: Description | D1: Probability | E1: Impact | F1: Mitigation / action | G1: Owner | H1: Status
A2: R-01 | B2: Risk | C2: Yahoo Finance is not established as an approved or licensed institutional market-data source. | D2: High | E2: High | F2: Obtain provider/data-rights decision in Sprint 2; keep production scope blocked until approved source is selected. | G2: Market Data Owner | H2: Open
A3: R-02 | B3: Risk | C3: Full-snapshot trade Bronze can leave stale Silver trades when trade IDs disappear from later files. | D3: Medium | E3: High | F3: Agree cancellation/deletion semantics and implement two-snapshot reconciliation test before relying on external trade feed. | G3: Trade Data Owner | H3: Open
A4: R-03 | B4: Risk | C4: Full-history recomputation and free-form instrument/book data may not scale or satisfy control expectations. | D4: Medium | E4: High | F4: Benchmark representative scale; establish reference ownership and incremental strategy from evidence. | G4: Lead Data Engineer | H4: Open
A5: R-04 | B5: Risk | C5: Eight-week plan has no capacity reserve and depends on part-time approvers and test runtime access. | D5: Medium | E5: High | F5: Reserve decision owners at Sprint start; defer dashboard polish or extend by one sprint if critical access/decisions slip. | G5: Project Manager | H5: Open
A6: A-01 | B6: Assumption | C6: Initial scope remains USD cash equities, 10 configured instruments, and one development workspace. | D6: N/A | E6: High | F6: Product owner confirms before Sprint 1 exit; FX, derivatives, fees, and corporate actions stay out of scope. | G6: Product Owner | H6: To confirm
A7: I-01 | B7: Issue | C7: A documented second same-parameter Databricks run was queued and has no recorded outcome. | D7: N/A | E7: Medium | F7: Run and compare business keys/values in a supported runtime; retain evidence. | G7: QA / Lead Engineer | H7: Open
A8: I-02 | B8: Issue | C8: Three focused local tests fail because they read removed Silver *_constraints.sql files; the checks now reside in consolidated trades.sql and market_prices.sql. | D8: N/A | E8: Medium | F8: Update stale test paths and assertions to the consolidated DDL, then rerun focused and full suite; application/test changes are outside this documentation task. | G8: Lead Engineer / QA | H8: Open
A9: D-01 | B9: Dependency | C9: Production environment, service principal, data rights, source owners, and reporting audience are not evidenced. | D9: High | E9: High | F9: Record named decision owner and due date; keep job schedule paused until readiness gate. | G9: Project Manager | H9: Open
A10: A-02 | B10: Assumption | C10: Two-week sprint estimates use 10 story points of lead-engineer delivery capacity per sprint, with part-time BA/architect/QA support. | D10: N/A | E10: Medium | F10: Re-estimate at planning; the eight-week baseline has no reserve and is not a committed calendar date. | G10: Project Manager | H10: Proposed

Sheet Traceability
A1: Business requirement | B1: Functional requirement | C1: Jira story | D1: Test case(s) | E1: Acceptance evidence | F1: Implementation status
A2: BR-001 | B2: FR-001 | C2: TMP-011 | D2: TC-001 | E2: tests/test_ingest_trades.py; capture supported-runtime run | F2: IMPLEMENTED
A3: BR-001 | B3: FR-003 | C3: TMP-015 | D3: TC-003 | E3: tests/test_trades.py; tests/test_process_prices.py | F3: IMPLEMENTED
A4: BR-001 | B4: FR-003 | C4: TMP-016 | D4: TC-003; TC-007 | E4: tests/test_trades.py; tests/test_process_prices.py; database/tables/**/*.sql; generated Data Dictionary worksheet; update tests that still reference removed *_constraints.sql paths | F4: PLANNED
A5: BR-001 | B5: FR-004 | C5: TMP-015 | D5: TC-003 | E5: tests/test_trades.py; tests/test_process_prices.py | F5: IMPLEMENTED
A6: BR-001 | B6: FR-004 | C6: TMP-012 | D6: TC-003 | E6: tests/test_trades.py; tests/test_process_prices.py | F6: PLANNED
A7: BR-001 | B7: FR-005 | C7: TMP-015 | D7: TC-003 | E7: tests/test_trades.py; tests/test_process_prices.py | F7: IMPLEMENTED
A8: BR-001 | B8: FR-005 | C8: TMP-016 | D8: TC-002; TC-003 | E8: tests/test_ingest_prices.py; test fixtures; tests/test_trades.py; tests/test_process_prices.py | F8: PLANNED
A9: BR-001 | B9: FR-013 | C9: TMP-016 | D9: TC-008; TC-009 | E9: New supported Databricks/Delta run pair; compare business-key hashes; Job run URL, audit rows, recovery run and reconciliation | F9: PLANNED
A10: BR-001 | B10: FR-013 | C10: TMP-022 | D10: TC-008 | E10: New supported Databricks/Delta run pair; compare business-key hashes | F10: PARTIALLY IMPLEMENTED
A11: BR-001 | B11: FR-013 | C11: TMP-024 | D11: TC-009; TC-012 | E11: Job run URL, audit rows, recovery run and reconciliation; Access review, CI/deploy log, alert test, runbook walkthrough | F11: PLANNED
A12: BR-002 | B12: FR-002 | C12: TMP-013 | D12: TC-002 | E12: tests/test_ingest_prices.py; test fixtures | F12: IMPLEMENTED
... A60: BR-008 | B60: FR-013 | C60: TMP-024 | D60: TC-009; TC-012 | E60: Job run URL, audit rows, recovery run and reconciliation; Access review, CI/deploy log, alert test, runbook walkthrough | F60: PLANNED

Sheet Test Plan
A1: Test ID | B1: Test level | C1: Scope | D1: Requirement IDs | E1: Jira story | F1: Expected result | G1: Acceptance evidence | H1: Status / note
A2: TC-001 | B2: Unit / file contract | C2: Trade CSV exact header, empty/malformed file, raw strings, dedupe, no overwrite on invalid input | D2: FR-001, FR-013 | E2: TMP-011 | F2: Valid file writes distinct snapshot; invalid source fails before overwrite | G2: tests/test_ingest_trades.py; capture supported-runtime run | H2: Planned / existing tests to rerun
A3: TC-002 | B3: Unit / integration | C3: Price response normalization, retries, date window, no-price handling | D3: FR-002, FR-005 | E3: TMP-013, TMP-014 | F3: Correct close records; missing expected sessions are explicit; no invented price | G3: tests/test_ingest_prices.py; test fixtures | H3: Planned / existing tests to rerun
A4: TC-003 | B4: Data quality | C4: Silver cast, rules, reject reasons, duplicate/version precedence | D4: FR-003, FR-004, FR-005 | E4: TMP-015 | F4: Valid typed rows only; deterministic rejects and one selected trade version | G4: tests/test_trades.py; tests/test_process_prices.py | H4: Planned / existing tests to rerun
A5: TC-004 | B5: Calculation / reconciliation | C5: Daily and cumulative position, buys/sells, no-trade day, short/flat, correction | D5: FR-006, FR-009 | E5: TMP-017, TMP-022 | F5: Gold quantity matches independent trade aggregation by full grain | G5: tests/test_build_positions.py; independent SQL reconciliation | H5: Planned / existing tests to rerun
A6: TC-005 | B6: Valuation | C6: Exact-date price, currency, missing mark, null valuation and break | D6: FR-007 | E6: TMP-017 | F6: Value = closing quantity * exact close; missing mark does not change quantity | G6: tests/test_build_positions.py; Gold break query | H6: Planned / existing tests to rerun
A7: TC-006 | B7: P&L reconciliation | C7: Opening-position price move + trade-day cash-flow term; missing baseline/current close | D7: FR-008 | E7: TMP-018, TMP-022 | F7: Financial values match independent Decimal calculation; missing inputs yield NULL | G7: tests/test_daily_pnl.py; documented BOOK_TECH/AAPL hand check | H7: Planned / existing tests to rerun
A8: TC-007 | B8: Schema | C8: DDL column/type/nullability/key assumptions and financial precision | D8: FR-003, FR-006, FR-008, FR-011 | E8: TMP-008, TMP-021 | F8: All 10 DDL tables appear in dictionary with exact SQL definitions | G8: database/tables/**/*.sql; generated Data Dictionary worksheet; update tests that still reference removed *_constraints.sql paths | H8: Planned / existing tests to rerun
A9: TC-008 | B9: Idempotency | C9: Same source snapshot/date range run twice | D9: FR-009, FR-013 | E9: TMP-016, TMP-022 | F9: Business values and unique keys stable; audit history reflects both attempts | G9: New supported Databricks/Delta run pair; compare business-key hashes | H9: Planned / existing tests to rerun
A10: TC-009 | B10: Recovery | C10: Inject source/task failure and rerun after correction | D10: FR-001, FR-011, FR-012, FR-013 | E10: TMP-016, TMP-024 | F10: Failure is audited, downstream blocked, corrected rerun reaches consistent outputs | G10: Job run URL, audit rows, recovery run and reconciliation | H10: Planned / existing tests to rerun
A11: TC-010 | B11: Workflow integration | C11: Six-task DAG, parallel source branches, Bundle parameters and deployment smoke test | D11: FR-012 | E11: TMP-009, TMP-010, TMP-023 | F11: Prices/trades branches run independently, join before positions, P&L runs last | G11: Bundle validate output; Job task graph and run record | H11: Planned / existing tests to rerun
A12: TC-011 | B12: Reporting / UAT | C12: Run status, row counts, rejects, breaks, positions, P&L, dashboard access | D12: FR-010, FR-011 | E12: TMP-019, TMP-020, TMP-022 | F12: Report/dashboard totals reconcile to Gold; unavailable measures are clearly labeled | G12: UAT scripts, screenshot/export, stakeholder sign-off | H12: Planned / existing tests to rerun
A13: TC-012 | B13: Deployment / operations | C13: Environment config, least privilege, notifications, recovery, handover | D13: FR-011, FR-012, FR-013 | E13: TMP-005, TMP-010, TMP-024 | F13: Approved identity and runbook are usable; schedule remains gated until readiness approval | G13: Access review, CI/deploy log, alert test, runbook walkthrough | H13: Planned / existing tests to rerun

Sheet Current State
A1: Area | B1: Capability | C1: Status | D1: Verified evidence | E1: Gap / limitation
A2: Source | B2: Trade input | C2: IMPLEMENTED | D2: Synthetic 14-field CSV; 1,200-row sample; UC Volume input | E2: No real trading-system connector; full snapshot and missing-ID semantics need business decision
A3: Source | B3: Market prices | C3: IMPLEMENTED | D3: yfinance unadjusted close; ten defaults; USD | E3: No approved/licensed production provider evidence
A4: Data | B4: Reference data | C4: PARTIALLY IMPLEMENTED | D4: Ten instrument mappings in Python config | E4: No persisted/effective-dated instruments, books, or counterparties
A5: Pipeline | B5: Bronze/Silver/Gold | C5: IMPLEMENTED | D5: 10 physical Delta tables; PySpark modules; validation, rejects, lineage | E5: No reporting schema/table or explicit table PK enforcement
A6: Calculations | B6: Positions/P&L | C6: IMPLEMENTED | D6: Position/P&L transforms and dated independent SQL reconciliation | E6: Simplified USD cash equities; no fees/FX/dividends/corporate actions
A7: Reporting | B7: Notebook and SQL | C7: IMPLEMENTED | D7: Run-trigger and read-only report notebooks; demo queries | E7: No deployed dashboard; report has known unavailable counters
A8: Operations | B8: Audit/recovery | C8: PARTIALLY IMPLEMENTED | D8: Task attempt logs; reject history; valuation breaks; safe rerun code | E8: No automated alerts; second identical Databricks run was queued in dated evidence
A9: Deployment | B9: Databricks Bundle | C9: PARTIALLY IMPLEMENTED | D9: Dev target, wheel build, deploy script; six-task Job | E9: Schedule paused; no CI/test/prod targets or production principal evidenced
A10: Testing | B10: pytest and Databricks run | C10: PARTIALLY IMPLEMENTED | D10: Dated run 2026-10-11: six tasks succeeded; positions 5,990 and P&L 835 reconciled with zero mismatches. Focused test run found 3 stale DDL-path failures. | E10: Tests expect removed trades_constraints.sql / market_prices_constraints.sql; constraints are in consolidated DDL. Second run unverified; Spark/Delta runtime required for full integration proof
